{
    "a": "3",
    "p": "3",
    "n": "33",
    "msknum": "0",
    "ssknum": "0",
    "balamanorama": "",
    "tattvabodhini": "",
    "padamanjari": " विस्तारःउ तिर्यगायतिः ॥",
    "kashika": "स्तृ̄ञाच्छादने, अस्माद् धातोः विशब्दे उपपदे घञ् पत्ययो भवति प्रथने गम्यमाने, तच् चेत् प्रथनं शब्दविषयं न भवति। प्रथनं विस्तीर्णता। पटस्य विस्तारः। प्रथने इति किम्? तृणविस्तरः। अशब्दे इति किम्? विस्तरो वचसाम्।",
    "sutra_vishesh": "कृत्प्रत्ययप्रकरणम् - भावे, कर्तृभिन्नकारके \"घञ्\" प्रत्ययविधानम्",
    "mahabhashyam": "",
    "sutra": "प्रथने वावशब्दे",
    "kaumudiNumber": "3204",
    "kaumudiText": "विपूर्वात् स्तृणातेर्घञ् स्यादशब्दविषये प्रथने | पटस्य विस्तारः | प्रथने किम् | तृणविस्तरः | अशब्दे किम् | ग्रन्थविस्तरः ॥",
    "nyaas": "`तृणविस्तरः` इति| तृणाच्छादनमित्यर्थः॥"
}


