{
    "a": "3",
    "p": "3",
    "n": "176",
    "s": "स्मोत्तरे लङ् च ",
    "padachcheda": "स्मोत्तरे ७\/१ लङ् १\/१ च ०\/०",
    "anuvritti": "माङि ७\/१ [3|3|175], लुङ् १\/१ [3|3|175]",
    "adhikara": " प्रत्यय: [3।1।1]  परश्च [3।1।2]  आद्युदात्तश्च [3।1।3]  धातो: [3।1।91] ",
    "full_sutra": "स्मोत्तरे माङि लुङ् लङ् च ",
    "siddhantakaumudi_index": "2220",
    "msknum": "464",
    "ssknum": "0",
    "balamanorama": "<<स्मोत्तरे लङ् च>> - स्मोत्तरे लङ् च । चकारान्माङि लुङित्यनुकृष्यते ।स्मे त्यव्ययमुत्तरं यस्मादिति विग्रहः । तदाह — -स्मोत्तरे माङिति । अयमपि सर्वलकारापवादः । ",
    "tattvabodhini": "",
    "padamanjari": "",
    "laghusiddhantakaumudi_index": "438",
    "laghusiddhantakaumudi": "स्मोत्तरे माङि लङ् स्याच्चाल्लुङ्॥",
    "kashika": "स्मशब्दौत्तरे माङि उपपदे धातोः लङ् प्रत्ययो भवति, चकाराल् लुग् च। मा स्म करोत्। मा स्म कार्षीत्। मा स्म हरत्। मा स्म हार्षीत्। इति श्रीजयादित्यविरचितायाम् काशिकायां वृत्तौ तृतीयाध्यायस्य तृतीयः पादः। तृतीयाध्यायस्य चतुर्थः पादः।",
    "mahabhashyam": "",
    "siddhantakaumudi": "स्मोत्तरे माङि लङ् स्याच्चाल्लुङ् ॥",
    "nyaas": "स्मशब्द उत्तरमधिकं यस्य माङः स तथोक्तः॥इति श्रीबोधिसत्त्वदेशीयाचार्यजिनेन्द्रबुद्धिपादविरचितायां काशिकाविवरणपञ्जिकायां तृतीयस्याध्यायस्यतृतीयः पादः"
}


