{
    "a": "4",
    "p": "4",
    "n": "13",
    "msknum": "0",
    "ssknum": "0",
    "balamanorama": "<<वस्नक्रयविक्रयाट्ठन्>> - वस्नक्रयविक्रयाट्ठन् । जीवतीत्यर्थे तृतीयान्तेभ्यो वस्नादिभ्यष्ठन् स्यादित्यर्थः । सङ्घातविगृहीतार्थमिति । व्याख्यानादिति भावः । ",
    "tattvabodhini": "",
    "padamanjari": " वसेर्वस्नमुमूल्यम् । क्रियविक्रयग्रहणं सङ्घातविगृहीतार्थमिति । उक्तोऽत्र हेतुः । क्रयविक्रयेणेति समाहारद्वन्द्वः ॥",
    "kashika": "वस्नक्रयविक्रयशब्दाभ्यां तृतीयासमर्थाभ्यां ठन् प्रत्ययो भवति जीवति इत्येतस्मिन् विषये। ठको ऽपवादः। वस्नेन जीवति वस्निकः। क्रयविक्रयग्रहणं सङ्घातविगृहीतार्थम्। क्रयविक्रयीकः। क्रयिकः। विक्रयिकः।",
    "sutra_vishesh": "",
    "mahabhashyam": "",
    "sutra": "वस्नक्रयविक्रयाट्ठन्",
    "kaumudiNumber": "1563",
    "kaumudiText": "वस्नेन मुल्येन जीवति वस्निकः | क्रयविक्रयग्रहणं संघातविगृहीतार्थम् | क्रयविक्रयिकः | क्रयिकः | विक्रयिकः ॥",
    "nyaas": "`क्रयविक्रयग्रहणं सङ्घातविगृहीतार्थम्` इति| इह तन्त्रेण क्रयविक्रयशब्दावुच्चारितौ;तत्रैकस्य सङ्घातार्थं ग्रहणम्, अपरस्य तु विगृहीतार्थं वेदितव्यम्॥"
}


