{
    "a": "5",
    "p": "2",
    "n": "86",
    "s": "पूर्वादिनिः ",
    "padachcheda": "पूर्वात् ५\/१  इनिः  १\/१",
    "anuvritti": " अनेन ३\/१ [5।2।85]",
    "adhikara": " प्रत्यय: [3।1।1]  परश्च [3।1।2]  आद्युदात्तश्च [3।1।3]  ङ्याप्प्रातिपदिकात् [4।1।1]  तद्धिता: [4।1।76] समर्थानां प्रथमाद्वा [4।1।82] ",
    "full_sutra": "\"अनेन\" (इति) पूर्वात् इनिः ",
    "siddhantakaumudi_index": "1886",
    "msknum": "2037",
    "ssknum": "0",
    "balamanorama": "<<पूर्वादिनिः>> - पूर्वादिनिः । अनेनेति कर्तृतृतीयान्तमनुवर्तते । कां क्रियां प्रति कर्तेत्याकाङ्क्षायां भुक्तं पीतमित्यादि यत्किञ्चित्क्रियापदमध्याहार्यम् । उपस्थितत्वात् कृञर्छभूतं क्रियासामान्यमेव प्रतीयते । ततश्च पूर्वं कृतमनेनेति विग्रहे कृतमित्यादिक्रियाविशेषणात्पूर्वशब्दादनेनेत्यर्थे इनिः स्यादित्यर्थः । ",
    "tattvabodhini": "<<पूर्वादिनिः>> - पूर्वादिनिः । पूर्वमिति क्रियाविशेषणाद्द्वितीयान्तात्प्रत्ययः ।अनेने॑ति कर्तृवाचकमनुवर्तते । न च क्रियामन्तरेण कर्ता संभवतीति कांचित्क्रियामध्याह्मत्य प्रत्ययो विधेयस्तदाह — -पूर्व कृतमनेनेति ।",
    "padamanjari": " पूर्वं गतमनेनेत्यादि। क्रियाविसेषणाद् द्वितीयान्तात्प्रत्ययः ॥",
    "laghusiddhantakaumudi_index": "1185",
    "laghusiddhantakaumudi": "पूर्वं कृतमनेन पूर्वी॥",
    "kashika": "अनेन इति प्रत्ययार्थः कर्ता ऽनुवर्तते। न च क्रियाम् अन्तरेण कर्ता सम्भवति इति यां काञ्चित् क्रियामध्याहृत्य प्रत्ययो विधेयः। पूर्वातनेन इत्यस्मिन्नर्थे इनिः प्रत्ययो भवति। पूर्वं गतम् अनेन पीतम् भुक्तं वा पूर्वी, पूर्विणौ, पूर्विणः।",
    "mahabhashyam": "",
    "siddhantakaumudi": "पूर्वं कृतमनेन पूर्वी ॥",
    "nyaas": "`पूर्व गतं पीतं भूक्तम्` इति| पूर्वशब्दोऽत्र क्रियाविशेषणत्वात्? कर्म भवतीति द्वितीयासमर्थात्? प्रत्ययो विज्ञायते| `पूर्वो` इति| `सौ च`  [[6|4|13]]  इति दीर्घः॥"
}


