{
    "a": "5",
    "p": "3",
    "n": "16",
    "s": "इदमो र्हिल् ",
    "padachcheda": "इदमः ५\/१ र्हिल्  १\/१",
    "anuvritti": " काले ७\/१ [5।3।15], सप्तम्याः 5\/1 [5।3।10]",
    "adhikara": " प्रत्यय: [3।1।1]  परश्च [3।1।2]  आद्युदात्तश्च [3।1।3]  ङ्याप्प्रातिपदिकात् [4।1।1]  तद्धिता: [4।1।76]  प्राग्दिशो विभक्ति: [5।3।1]  किंसर्वनामबहुभ्योऽद्व्यादिभ्यः [5।3।2] वा [4।1।82]",
    "full_sutra": "इदमः सप्तम्याः काले र्हिल् ",
    "siddhantakaumudi_index": "1965",
    "msknum": "2092",
    "ssknum": "0",
    "balamanorama": "<<इदमो र्हिल्>> - इदमो र्हिल् । इदमः — र्हिल् इति च्छेदः । एतर्हीति । इदम्शब्दात् र्हिल् ।एतेतौ रथो॑रित्येतादेशः । ",
    "tattvabodhini": "<<इदमो र्हिल्>> - एतर्हीति ।एततौ रथोः॑एत्येतादेशः ।",
    "padamanjari": " लकारः स्वरार्थ इति। यथा हीत इत्यत्र ठूडिदम्ऽ इत्यादिना स्वरो भवति, तथेह न भवति; लित्वस्याचरीतार्थत्वात्। तसिलस्तु लित्वलमिदमोऽन्यत्र चरितार्थम् ॥",
    "laghusiddhantakaumudi_index": "1214",
    "laghusiddhantakaumudi": "सप्तम्यन्तात् काल इत्येव॥",
    "kashika": "सप्तम्याः इत्येव, काले इति च। इदमः सप्तम्यन्तात् काले वर्तमानात् र्हिल् प्रत्ययो भवति। हस्य अपवादः। लकारः स्वरार्थः। अस्मिन् काले एतर्हि। काले इत्येव, इह देशे।",
    "mahabhashyam": "",
    "siddhantakaumudi": "सप्तम्यन्तात्काले इत्येव | हस्यापवादः | अस्मिन्काले एतर्हि | काले किम् | इह देशे ॥",
    "nyaas": "`हस्यापवादः` इति| `इदमो हः`  [[5|3|11]]  इति प्राप्तस्य| `लकारः स्वरार्थः` इति| `लिति` [[6|1|193]]  प्रत्ययात्? पूर्वस्योदात्तत्वं यथा स्यात्| ननु च यथा इत इत्यत्र--`ऊडिदम्`  [[6|1|165]]  इत्यादिना विभक्तिस्वरो भवति, तथेहापि तेनैव भवितव्यम्? नैतदस्ति; तथा हि युक्तमित इत्यत्र यद्विभक्तिस्वरो भवतीति; तसिलो लित्त्वस्य परितः, अभित इत्यतर चरितार्थत्वात्, अस्य तु हिलो लित्करणमकृतार्थम्| तद्यदि विभक्तिस्वरेम बाध्येत तस्यानर्थक्यं स्यात्| तस्माल्लित्स्वर एव भवति॥"
}


