{
    "a": "5",
    "p": "3",
    "n": "50",
    "msknum": "0",
    "ssknum": "0",
    "balamanorama": "<<षष्ठाष्टमाभ्यां ञ च>> - षष्ठाष्टमाभ्यां ञ च । \"पूर्वसूत्रविषये\" इति शेषः ।ञे॑ति लुप्तप्रथमाकम् । ञे आदिवृद्दिः । चादनिति । इह न यथासह्ख्यं, व्याख्यानात् । ",
    "tattvabodhini": "",
    "padamanjari": " यथासंख्यमत्र न भवति, अन्यतरस्मादनः पूर्वेणैव सिद्धत्वात् ॥",
    "kashika": "भागे इत्येव, अच्छन्दसि इति च। षष्ठाष्टमभ्यां भागे अभिधेये अच्छन्दसि विषये ञः प्रत्ययो भवति। चकारादन् च। षष्ठो भागः षष्टः, षष्ठः। आष्टमः, अष्टमः।",
    "sutra_vishesh": "",
    "mahabhashyam": "",
    "sutra": "षष्ठाष्टमाभ्यां ञ च",
    "kaumudiNumber": "1996",
    "kaumudiText": "चादन् | षष्ठो भागः | षाष्ठः | षष्ठः | आष्टमः | अष्टमः ॥",
    "nyaas": "यथासंख्ये हि षष्ठादन्यथा प्राप्तं चेत्यन्| न च पूर्वेणैव सिद्ध इति षष्ठग्रहमनर्थकं स्यात्| तस्मादुभयाभ्यामुभयं भवति॥"
}


