{
    "a": "5",
    "p": "4",
    "n": "134",
    "msknum": "1565",
    "ssknum": "0",
    "balamanorama": "",
    "tattvabodhini": "",
    "padamanjari": "",
    "kashika": "जायाशब्दान्तस्य बहुव्रीहेर् निङादेशः भवति। युवतिः जाया यस्य युवजानिः। वृद्धजानिः।",
    "sutra_vishesh": "",
    "mahabhashyam": "",
    "sutra": "जायाया निङ्",
    "kaumudiNumber": "872",
    "kaumudiText": "जायान्तस्य बहुव्रीहेर्निङादेशः स्यात् ॥",
    "nyaas": "`निङादेशो भवति` इति| आदेशत्वमस्य पूर्ववद्? ङित्त्वादेव विज्ञायते| `युवजानिः` इति| लोपो व्योर्वलि`  [[6|1|64]]  इति यलोपः| `स्त्रियाः पुंवत्`  [[6|3|33]]  इति पुंवद्भावः॥"
}


