{
    "a": "7",
    "p": "1",
    "n": "87",
    "s": "थो न्थः ",
    "padachcheda": "थः ६\/१ न्थः १\/१",
    "anuvritti": "सर्वनामस्थाने [7।1।86] ७\/१ , पथिमथ्यृभुक्षाम् [7।1।85] ६\/३ ",
    "adhikara": " अङ्गस्य [6।4।1] ",
    "full_sutra": "पथि-मथि-ऋभुक्षाम् अङ्गस्य थ: सर्वनामस्थाने  न्थ: ",
    "siddhantakaumudi_index": "367",
    "msknum": "317",
    "ssknum": "274",
    "balamanorama": "<<थो न्थः>> - थो न्थः । थः न्थ इति च्छेदः । थ इति षष्ठी । आदेशेऽकार उच्चारणार्थः । पथिमथिग्रहणमनुवर्तते । ऋभुक्षिग्रहणं निवृत्तं, तत्र थकाराऽभावात् ।इतोऽत्सर्वनामस्थाने॑ इत्यतः सर्वनामस्थानग्रहणमनुवर्तते । तदाह — पथिमथोरित्यादिना । पन्था इति । नकारस्य आत्त्वे इकारस्य अत्त्वे थकारस्य न्थादेशे पन्थ आ स् इति स्थिते सवर्णदीर्घे रुत्वविसर्गाविति भावः । पन्थानाविति । पथिन् औ इति स्थिते सावित्युक्तेर्नात्त्वम् \"इतोऽत्\" इति इकारस्याऽत्त्वे थकारस्य न्थादेशेसर्वनामस्थाने चे॑ति दीर्घे रूपमिति भावः ।",
    "tattvabodhini": "<<थो न्थः>> - थो न्थः । स्थान्यदेशौ द्वावप्यनच्कौ ।थेर्न्थः॑इत्येव सिद्धेइतोऽत्सर्वनामस्थाने॑इत्येतद्दभुक्षिन्नर्थं । त्रयाणाननुवृत्तापि ऋभुक्षस्थो न संभवतीत्याशयेनाह — -",
    "padamanjari": "  पथिमथोरिति । त्रयाणां प्रकृतत्वेऽप्येतयोरेव थकारसम्भवात् सम्बन्धः । आदेशेऽकार उच्चारणार्थः । स्यादेतत् - थेरन्थः इति सूत्रमस्तु, अकारोऽपि विवक्षितोऽस्तु ,थिशब्दस्यान्थ आदेशः एवं च कृत्वा इतोऽत् इति न वक्तव्यम् इति तदपि वक्तव्यम् ऋभुक्षिन्शब्दार्थम् ॥",
    "laghusiddhantakaumudi_index": "297",
    "laghusiddhantakaumudi": "पथिमथोस्थस्य न्थादेशः सर्वनामस्थाने। पन्थाः। पन्थानौ। पन्थानः॥",
    "kashika": "पथिमथोः थकारस्य स्थाने न्थः इत्ययम् आदेशो भवति सर्वनामस्थाने परतः। पन्थाः, पन्थानौ, पन्थानः। मन्थाः, मन्थानौ, मन्थानः।",
    "mahabhashyam": "",
    "siddhantakaumudi": "पथिमथोस्थस्य न्थादेशः स्यात्सर्वनामस्थाने परे | पन्था | पन्थानौ | पन्थानः | पन्थानम् | पन्थानौ ॥",
    "nyaas": "थः, न्थः--इति द्वावपि स्थान्यादेशावनच्कौ| यत्त्त्वन्थ इत्यत्राकारः श्रूयते स उच्चारणार्थः| सत्यप्यादेशस्यानेकाल्त्वे `निर्दिश्यमानस्यादेशा भवन्ति` (व्या|प|106) इति थकारमात्रस्यादेशो विज्ञायते, न सर्वस्य॥"
}


