{
    "a": "7",
    "p": "4",
    "n": "50",
    "s": "तासस्त्योर्लोपः ",
    "padachcheda": "तासस्त्योः ६\/२ लोपः १\/१",
    "anuvritti": "स: 6\/1 [7।4।49],  सि 7\/1 [7।4।59]",
    "adhikara": " अङ्गस्य [6।4।1] ",
    "full_sutra": "तास्-अस्त्यो: स: अङ्गस्य सि लोप: ",
    "siddhantakaumudi_index": "2191",
    "msknum": "435",
    "ssknum": "376",
    "balamanorama": "<<तासस्त्योर्लोपः>> - तदाह — तासस्त्योः । \"सः स्यार्धधातुके\" इत्यतः सीत्यनुवर्तते, अङ्गाक्षिप्तस्य प्रत्ययस्य सीत्यनेन विशेषणात्यस्मिन्विधि॑रिति तदादिविधिः, तदिदमाह — सादाविति । एवं रादावित्त्राप्यूह्रम् । ",
    "tattvabodhini": "<<तासस्त्योर्लोपः>> - ॒सः स्यार्धदातुके॑ इत्यतः सीत्यनुवर्तते, अङ्गाक्षिप्तस्य प्रत्ययस्य सीत्यनेन विशेषणात्यस्मिन्विधि॑रिति तदादिविधिः, तदिदमाह —  सादाविति । एवं रादावित्यत्राप्यूह्रम् ।",
    "padamanjari": " व्यतिसे इति । ठ्कर्तरि कर्मव्यतिहारेऽ इत्यात्मनेपदम्, शपो लुक्, ठ्श्नसोरल्लोपःऽ इत्यकारलोपः । प्रत्ययमात्रमेतत्पदमिति । तेन ठ्सात्पदाद्योःऽ इति षत्वप्रतिषेध इति भावः ॥",
    "laghusiddhantakaumudi_index": "408",
    "laghusiddhantakaumudi": "तासेरस्तेश्च सस्य लोपस्स्यात् सादौ प्रत्यये परे।",
    "kashika": "तासेः अस्तेश्च सकारस्य सकारादौ प्रत्यये परतः लोपो भवति। तासेः कर्तासि। कर्तासे। अस्तेः त्वम् असि। व्यतिसे। अस्तेः अकारासकारयोः लुप्तयोः से इति प्रत्ययमात्रम् एतत् पदम्, तेन सात् पदाद्योः [[8|3|111]] इति षत्वं न भवति।",
    "mahabhashyam": "",
    "siddhantakaumudi": "दासेरस्तेश्च लोपः स्यात्सादौ प्रत्यये परे ॥",
    "nyaas": "`अनद्यतने लुट्`  [[3|3|15]]  तासिः, सिप्| `कत्र्तासे` इति| `थासः से`  [[3|4|80]] | `त्वमसि` इति| `स भुवि` (धातुपाठः-1065), पूर्ववच्छपो लुक्| `व्यतिसे` इति| `कत्र्तरि कर्मव्यतीहारे`  [[1|3|14]]  इत्यात्मनेपदं भवति| `थासः से`  [[3|4|80]] , `श्नसोरल्लोपः`  [[6|4|111]]  इत्यकारलोपः| अथ `आदेशप्रत्यययोः`  [[8|3|59]]  इति षत्वं कस्मान्न भवति? इत्यत आह--`अस्तेरकारसकारयोः` इत्यादि| अकारसकारयोर्हि लुप्तयोः प्रत्ययमात्रमवशिष्यते, तदेव पदम, अतः `सात्पदाद्योः`  [[8|3|111]]  इति प्रतिषेधात्? षत्वं न भविष्यतीति भावः॥"
}


